{
  "project_info": {
    "project_number": "750774149943",
    "project_id": "grewal-academy-d44be",
    "storage_bucket": "grewal-academy-d44be.appspot.com"
  },
  "client": [
    {
      "client_info": {
        "mobilesdk_app_id": "1:750774149943:android:95dede6774ae26598ab0b2",
        "android_client_info": {
          "package_name": "com.grewal.grewal"
        }
      },
      "oauth_client": [
        {
          "client_id": "750774149943-me8p981iql7l0cjdm69j604q41k5nk5k.apps.googleusercontent.com",
          "client_type": 3
        }
      ],
      "api_key": [
        {
          "current_key": "AIzaSyAeJ9Xk70XW5k2mZoesusB8lx2NrUNUQ1o"
        }
      ],
      "services": {
        "appinvite_service": {
          "other_platform_oauth_client": [
            {
              "client_id": "750774149943-me8p981iql7l0cjdm69j604q41k5nk5k.apps.googleusercontent.com",
              "client_type": 3
            },
            {
              "client_id": "750774149943-gpahm08huq2u3idcau1gsefagvafk5r1.apps.googleusercontent.com",
              "client_type": 2,
              "ios_info": {
                "bundle_id": "com.grewal.grewal"
              }
            }
          ]
        }
      }
    }
  ],
  "configuration_version": "1"
}